{
    "elldrethsVividMix_v20VividEr.safetensors [0f7f264114]": "0f7f264114",
    "fkingScifiV2_r41958.safetensors [d6a44b9b90]": "d6a44b9b90",
    "furtasticv11_furtasticv11.safetensors [8708576421]": "8708576421",
    "futagen_2.safetensors [08946cce7d]": "08946cce7d",
    "galaxytimemachinesGTM_v1.safetensors [e406a20c1b]": "e406a20c1b",
    "Grapefruit.safetensors [4fc8d3739f]": "4fc8d3739f",
    "grapeGrapefruitHenta_grapefruitV11.safetensors [4a6e5cd1c8]": "4a6e5cd1c8",
    "GrapeLikeDreamFruit.ckpt [c9278e23a7]": "c9278e23a7",
    "gta5ArtworkDiffusion_v1.ckpt [607aa02fb8]": "607aa02fb8",
    "hAS3Dkx10B_3Dkx10B.safetensors [1d45c7c094]": "1d45c7c094",
    "HAs_3DKX 1.1.ckpt [998f6b580e]": "998f6b580e",
    "hasdx_hasedsdx.safetensors [fafc72c6fd]": "fafc72c6fd",
    "hassanblend1512And_hassanblend1512.safetensors [f05dd9e62f]": "f05dd9e62f",
    "hassanBlendAllVersio_hassanBlend14.safetensors [b08fdba169]": "b08fdba169",
    "Healys_Anime_Blend.ckpt [8416edf88c]": "8416edf88c",
    "healySAnimeBlend_17.ckpt [8416edf88c]": "8416edf88c",
    "homoerotic_v2.safetensors [b656369cf7]": "b656369cf7",
    "Inkpunk-Diffusion-v2.ckpt [2182245415]": "2182245415",
    "instruct-pix2pix-00-22000.safetensors [fbc31a67aa]": "fbc31a67aa",
    "jaksCreepyCritter_sd21768px.ckpt [67d399388b]": "67d399388b",
    "jhSSamdoesarts_v5.ckpt [dfba164825]": "dfba164825",
    "kenshi_00.safetensors [8c19d5c981]": "8c19d5c981",
    "knollingcase_v1.ckpt [cf836e65a7]": "cf836e65a7",
    "kotosAbyssproto_v10.safetensors [35d51ba12c]": "35d51ba12c",
    "ligneClaireAnime_v1.safetensors [672977e447]": "672977e447",
    "majorXs2DPOVModel_2dpov11.ckpt [83f9dcde52]": "83f9dcde52",
    "mandarine_3.ckpt [7a134798ee]": "7a134798ee",
    "mixProV3_v3.safetensors [b6928134bb]": "b6928134bb",
    "modernDisney_v1.ckpt [8067368533]": "8067368533",
    "moistmix_v2.safetensors [6514f58b5e]": "6514f58b5e",
    "openjourney-v2.ckpt [2fbe5ba6e2]": "2fbe5ba6e2",
    "openjourneyAka_v1.ckpt [5d5ad06cc2]": "5d5ad06cc2",
    "owlerartStyle_v2.safetensors [a31fe6f791]": "a31fe6f791",
    "pastelMixStylizedAnime_pastelMixPrunedFP16.safetensors [d01a68ae76]": "d01a68ae76",
    "pfg_111Safetensors.safetensors [ca42a7a009]": "ca42a7a009",
    "princessZeldaLora_v1.safetensors [53d6abf3cb]": "53d6abf3cb",
    "protogenV22Anime_22.safetensors [1254103966]": "1254103966",
    "protogenX34Photoreal_1.safetensors [44f90a0972]": "44f90a0972",
    "protogenX34Photorealism_1.safetensors [44f90a0972]": "44f90a0972",
    "protogenX58RebuiltSc_10.safetensors [6a21b428a3]": "6a21b428a3",
    "protogenX58RebuiltScifi_10.safetensors [6a21b428a3]": "6a21b428a3",
    "purepornplusMerge_purepornplus10.ckpt [40c6475ecb]": "40c6475ecb",
    "qgo10a_qgo10a.safetensors [7dd744682a]": "7dd744682a",
    "ratnikamix_2.safetensors [b6a8298a89]": "b6a8298a89",
    "realeldenapocalypse_Analogsexknoll.safetensors [7c7dfbd636]": "7c7dfbd636",
    "realisticVisionV13_v12.safetensors [8194f84cdc]": "8194f84cdc",
    "redshiftDiffusion_v1.ckpt [ed8c2ee432]": "ed8c2ee432",
    "roboeticsMix_rmix01Ckpt.ckpt [a7bd5ab091]": "a7bd5ab091",
    "RPG.ckpt [234bfa6e72]": "234bfa6e72",
    "s1dlxbrew_02.safetensors [1bf13ffc5d]": "1bf13ffc5d",
    "schoolAnime_schoolAnime.safetensors [36b0e74c02]": "36b0e74c02",
    "schoolmax25d_11.ckpt [0ce764ebd5]": "0ce764ebd5",
    "sd-v1-4.ckpt [fe4efff1e1]": "fe4efff1e1",
    "sd-v1-5-inpainting.ckpt [c6bbc15e32]": "c6bbc15e32",
    "shadyArtOFFICIAL_shadyArt1.safetensors [8f0cb2925d]": "8f0cb2925d",
    "spybgsToolkitFor_v40YoutubeChannel.ckpt [f277c5bba1]": "f277c5bba1",
    "StablyDiffuseds_Aesthetic_Mix.ckpt [03df69045a]": "03df69045a",
    "stablydiffusedsWild_3.safetensors [11a67baf56]": "11a67baf56",
    "superheroDiffusion_v1.ckpt [cac0a972cf]": "cac0a972cf",
    "surugaModel_suruga12K.ckpt [7846746c94]": "7846746c94",
    "synthwavepunk_v2.ckpt [dc4c67171e]": "dc4c67171e",
    "theAllysMix_v10Safetensors.safetensors [a18773a6bc]": "a18773a6bc",
    "theallysMixIIChurned_v10.safetensors [b000c45ea5]": "b000c45ea5",
    "uberRealisticPornMerge_urpmv12.safetensors [fcfaf106f2]": "fcfaf106f2",
    "unstableinkdream_v6.safetensors [d855c1d2ba]": "d855c1d2ba",
    "v1-5-pruned.ckpt [e1441589a6]": "e1441589a6",
    "v2-1_768-nonema-pruned.ckpt [4711ff4dd2]": "4711ff4dd2",
    "wd-v1-3-full.ckpt [23ba8d0411]": "23ba8d0411",
    "wlop_1.ckpt [b8cff3e33f]": "b8cff3e33f",
    "yiffymix_.safetensors [d6deb44e68]": "d6deb44e68",
    "\u5565\u73a9\u610f\u5b8c\u728a\u5b50F16.safetensors [dda725ba6e]": "dda725ba6e",
    "v1-5-pruned-emaonly.ckpt [cc6cb27103]": "cc6cb27103",
    "deliberate_v2.safetensors [9aba26abdf]": "9aba26abdf",
    "deliberate_v2.safetensors [38108d96f8]": "38108d96f8",
    "realisticVisionV20_v20.ckpt [eaf3051d80]": "eaf3051d80",
    "deliberate_v2.safetensors [d75347f3f0]": "d75347f3f0",
    "deliberate_v2.safetensors [b500405cde]": "b500405cde",
    "deliberate_v2.safetensors [493484f455]": "493484f455",
    "deliberate_v2.safetensors [ade8822b56]": "ade8822b56",
    "realisticVisionV20_v20.ckpt [d11a449e0f]": "d11a449e0f",
    "2dn_1.safetensors [83569a04f4]": "83569a04f4",
    "21SDModernBuildings_midjourneyBuildings.ckpt [14e1e8d692]": "14e1e8d692",
    "AbyssOrangeMix2_hard.safetensors [0fc198c490]": "0fc198c490",
    "adobisRealFlexibleMix_v2.safetensors [9e8a2c7a5d]": "9e8a2c7a5d",
    "allInOnePixelModel_v1.ckpt [d7fb6396ab]": "d7fb6396ab",
    "aloeverasSimpmaker3K_simpmaker3K1.ckpt [2cae9bc4e0]": "2cae9bc4e0",
    "analogDiffusion_10Safetensors.safetensors [51f6fff508]": "51f6fff508",
    "analogDream3D_10.ckpt [4575363662]": "4575363662",
    "anovel_speed.ckpt [89d59c3dde]": "89d59c3dde",
    "anygenV37_anygenv37.ckpt [815c974757]": "815c974757",
    "Anything-V3.0-pruned.ckpt [543bcbc212]": "543bcbc212",
    "anytwam11Mixedmodel_anytwam11.safetensors [e9cb790ad3]": "e9cb790ad3",
    "aoaokoPVCStyleModel_pvcAOAOKO.safetensors [cf64507cef]": "cf64507cef",
    "Arcane_Diffusion.ckpt [7dd0e6760f]": "7dd0e6760f",
    "arcaneDiffusion_v3.ckpt [7dd0e6760f]": "7dd0e6760f",
    "artErosAerosATribute_aerosNovae.safetensors [70346f7a1e]": "70346f7a1e",
    "aToZovyaRPGArtistsTools15_sd15V1.safetensors [e28b2e61fb]": "e28b2e61fb",
    "ayonimix_V2.safetensors [7076f76b9d]": "7076f76b9d",
    "babes_11.safetensors [79886b6484]": "79886b6484",
    "Basil_mix_fixed.safetensors [0ff127093f]": "0ff127093f",
    "biggerGirlsModel_biggergirlsV2.ckpt [f3c16c83de]": "f3c16c83de",
    "cheeseDaddys_30.safetensors [4176564bea]": "4176564bea",
    "chillout_west_mix.safetensors [b93a715b47]": "b93a715b47",
    "chilloutmix_inpainting.inpainting.safetensors [ec749031ba]": "ec749031ba",
    "chromaticcreamv1_chromaticcreamV1.ckpt [c979d60b4a]": "c979d60b4a",
    "ChromaV5 (2.0).ckpt [e8004ba771]": "e8004ba771",
    "clarity_14.safetensors [dc027dbbf9]": "dc027dbbf9",
    "classicNegative1521_classicNegative768px.ckpt [2106fd3b8c]": "2106fd3b8c",
    "Colorwater_v4.safetensors [1b175706ff]": "1b175706ff",
    "comicBabes_v1.safetensors [9211801e30]": "9211801e30",
    "comicDiffusion_v2.ckpt [d3c225cbc2]": "d3c225cbc2",
    "corneos7thHeavenMix_100.safetensors [d289dfa4ed]": "d289dfa4ed",
    "corneos7thHeavenMix_v1.safetensors [d289dfa4ed]": "d289dfa4ed",
    "Counterfeit-V2.5_pruned.safetensors [a074b8864e]": "a074b8864e",
    "CounterfeitV20_20.ckpt [8838e0d1fb]": "8838e0d1fb",
    "cuteRichstyle15_cuteRichstyle.ckpt [24bc802fc5]": "24bc802fc5",
    "cyberrealistic_v13.safetensors [23e4391b10]": "23e4391b10",
    "cynthiaModela_v10.safetensors [c83fe90aa3]": "c83fe90aa3",
    "deliberate_v11-inpainting.inpainting.safetensors [0d0792451f]": "0d0792451f",
    "deliberate_v11.safetensors [d8691b4d16]": "d8691b4d16",
    "dgspitzerArt_dgspitzerArtDiffusion.safetensors [8141c5f18e]": "8141c5f18e",
    "diGiMDSToriyamaModel_toriyamaV1.ckpt [33c84ed0b3]": "33c84ed0b3",
    "dreamlikeDiffusion10_10.ckpt [0aecbcfa2c]": "0aecbcfa2c",
    "dreamlikePhotoreal20_dreamlikePhotoreal20.safetensors [92970aa785]": "92970aa785",
    "dreamshaper_332BakedVaeClipFix.safetensors [13dfc9921f]": "13dfc9921f",
    "DucHaitenAIart.safetensors [55fed17365]": "55fed17365",
    "duchaitenaiart_V20.safetensors [55fed17365]": "55fed17365",
    "dvarchMultiPrompt_dvarchExterior.ckpt [1ecb6b4e9c]": "1ecb6b4e9c",
    "Elldreths_OG_4060_mix.ckpt [707ee16b5b]": "707ee16b5b",
    "Elldreths_Retro_Mix.ckpt [57285e7bd5]": "57285e7bd5",
    "ElldrethsImaginationMix.ckpt [64224f0599]": "64224f0599",
    "elldrethsLucidMix_v10.safetensors [67abd65708]": "67abd65708",
    "elldrethSOg4060Mix_v10.ckpt [707ee16b5b]": "707ee16b5b",
    "elldrethsRetroMix_v10.safetensors [57285e7bd5]": "57285e7bd5",
    "icomix_V02Pruned.safetensors [76b00ee812]": "76b00ee812",
    "inkpunkDiffusion_v2-inpainting-fp16-no-ema.safetensors [0c666f32e8]": "0c666f32e8",
    "inkpunkDiffusion_v2-inpainting.safetensors [1bd4ce2c12]": "1bd4ce2c12",
    "inkpunkDiffusion_v2.ckpt [2182245415]": "2182245415",
    "meinamix_meinaV8.safetensors [30953ab0de]": "30953ab0de",
    "mimi_V3.safetensors [88f31afc3d]": "88f31afc3d",
    "mini_town_v1.safetensors [ed94110348]": "ed94110348",
    "pixhell_v20.safetensors [333825e530]": "333825e530",
    "projectUnrealEngine5_projectUnrealEngine5B.ckpt [748ff6eab2]": "748ff6eab2",
    "pyraMythraPneuma_50Epochs.safetensors [fc9d093614]": "fc9d093614",
    "realisticVisionV20_v20.safetensors [c0d1994c73]": "c0d1994c73",
    "realLifeTest_realLifeTest.ckpt [d6347268cc]": "d6347268cc",
    "revAnimated_v11.safetensors [d725be5d18]": "d725be5d18",
    "samdoesartsUltmerge_v1.ckpt [0df9497424]": "0df9497424",
    "shanshui_v0-000002.safetensors [18cbf1953b]": "18cbf1953b",
    "tmndMix_tmndMixPlus.safetensors [7d19f9efad]": "7d19f9efad",
    "unstableinkdream_v73.safetensors [f036d7b40b]": "f036d7b40b",
    "unstablephotorealv5_05.ckpt [6ef4ed10a6]": "6ef4ed10a6",
    "yinmu.safetensors [c1b28e2883]": "c1b28e2883",
    "protogenX58RebuiltScifi_10.ckpt [e0de8aae3e]": "e0de8aae3e",
    "marvelWhatIf_v2.ckpt [2e051600d4]": "2e051600d4",
    "meinamix_meinaV9.safetensors [eac6c08a19]": "eac6c08a19"
}